{
    "id": 13,
    "name": "Ixcoin",
    "symbol": "IXC",
    "quotes": [
        {
            "timeOpen": "2021-11-01T00:00:00.000Z",
            "timeClose": "2021-11-01T23:59:59.999Z",
            "timeHigh": "2021-11-01T11:09:02.000Z",
            "timeLow": "2021-11-01T04:04:02.000Z",
            "quote": {
                "open": 0.1014828751,
                "high": 0.1033034529,
                "low": 0.098795528,
                "close": 0.1009576671,
                "volume": 0.0,
                "marketCap": 2142397.72,
                "timestamp": "2021-11-01T23:59:59.999Z"
            }
        },
        {
            "timeOpen": "2021-11-02T00:00:00.000Z",
            "timeClose": "2021-11-02T23:59:59.999Z",
            "timeHigh": "2021-11-02T16:03:02.000Z",
            "timeLow": "2021-11-02T00:46:02.000Z",
            "quote": {
                "open": 0.1009622953,
                "high": 0.1063218255,
                "low": 0.1004139067,
                "close": 0.1046077549,
                "volume": 0.0,
                "marketCap": 2219886.82,
                "timestamp": "2021-11-02T23:59:59.999Z"
            }
        },
        {
            "timeOpen": "2021-11-03T00:00:00.000Z",
            "timeClose": "2021-11-03T23:59:59.999Z",
            "timeHigh": "2021-11-03T07:59:02.000Z",
            "timeLow": "2021-11-03T18:02:02.000Z",
            "quote": {
                "open": 0.1046396938,
                "high": 0.1051205317,
                "low": 0.1012599175,
                "close": 0.1042042963,
                "volume": 0.0,
                "marketCap": 2211352.62,
                "timestamp": "2021-11-03T23:59:59.999Z"
            }
        },
        {
            "timeOpen": "2021-11-04T00:00:00.000Z",
            "timeClose": "2021-11-04T23:59:59.999Z",
            "timeHigh": "2021-11-04T00:32:02.000Z",
            "timeLow": "2021-11-04T18:05:02.000Z",
            "quote": {
                "open": 0.1042154285,
                "high": 0.1044690432,
                "low": 0.1006234414,
                "close": 0.1017434211,
                "volume": 0.0,
                "marketCap": 2159155.75,
                "timestamp": "2021-11-04T23:59:59.999Z"
            }
        },
        {
            "timeOpen": "2021-11-05T00:00:00.000Z",
            "timeClose": "2021-11-05T23:59:59.999Z",
            "timeHigh": "2021-11-05T06:12:02.000Z",
            "timeLow": "2021-11-05T20:42:02.000Z",
            "quote": {
                "open": 0.1017034416,
                "high": 0.103506129,
                "low": 0.1006978256,
                "close": 0.1011544066,
                "volume": 0.0,
                "marketCap": 2146683.45,
                "timestamp": "2021-11-05T23:59:59.999Z"
            }
        },
        {
            "timeOpen": "2021-11-06T00:00:00.000Z",
            "timeClose": "2021-11-06T23:59:59.999Z",
            "timeHigh": "2021-11-06T22:15:02.000Z",
            "timeLow": "2021-11-06T12:21:02.000Z",
            "quote": {
                "open": 0.1011629909,
                "high": 0.1415486287,
                "low": 0.0995710585,
                "close": 0.1415443905,
                "volume": 109.66,
                "marketCap": 3003866.1,
                "timestamp": "2021-11-06T23:59:59.999Z"
            }
        },
        {
            "timeOpen": "2021-11-07T00:00:00.000Z",
            "timeClose": "2021-11-07T23:59:59.999Z",
            "timeHigh": "2021-11-07T23:57:02.000Z",
            "timeLow": "2021-11-07T15:31:02.000Z",
            "quote": {
                "open": 0.1415132081,
                "high": 0.1443120865,
                "low": 0.1408640861,
                "close": 0.1443024465,
                "volume": 32.81,
                "marketCap": 3062441.94,
                "timestamp": "2021-11-07T23:59:59.999Z"
            }
        },
        {
            "timeOpen": "2021-11-08T00:00:00.000Z",
            "timeClose": "2021-11-08T23:59:59.999Z",
            "timeHigh": "2021-11-08T23:36:02.000Z",
            "timeLow": "2021-11-08T00:00:02.000Z",
            "quote": {
                "open": 0.144385535,
                "high": 0.1624169739,
                "low": 0.144385535,
                "close": 0.1621770807,
                "volume": 125.46,
                "marketCap": 3441807.64,
                "timestamp": "2021-11-08T23:59:59.999Z"
            }
        },
        {
            "timeOpen": "2021-11-09T00:00:00.000Z",
            "timeClose": "2021-11-09T23:59:59.999Z",
            "timeHigh": "2021-11-09T04:00:02.000Z",
            "timeLow": "2021-11-09T19:43:02.000Z",
            "quote": {
                "open": 0.1621603922,
                "high": 0.1644728152,
                "low": 0.0918362018,
                "close": 0.0924674808,
                "volume": 0.01,
                "marketCap": 1962406.19,
                "timestamp": "2021-11-09T23:59:59.999Z"
            }
        },
        {
            "timeOpen": "2021-11-10T00:00:00.000Z",
            "timeClose": "2021-11-10T23:59:59.999Z",
            "timeHigh": "2021-11-10T19:55:02.000Z",
            "timeLow": "2021-11-10T06:36:03.000Z",
            "quote": {
                "open": 0.0924211228,
                "high": 0.1266603732,
                "low": 0.0915206241,
                "close": 0.1226779381,
                "volume": 0.0,
                "marketCap": 2603579.29,
                "timestamp": "2021-11-10T23:59:59.999Z"
            }
        },
        {
            "timeOpen": "2021-11-11T00:00:00.000Z",
            "timeClose": "2021-11-11T23:59:59.999Z",
            "timeHigh": "2021-11-11T07:50:02.000Z",
            "timeLow": "2021-11-11T02:43:03.000Z",
            "quote": {
                "open": 0.1228409835,
                "high": 0.1490846477,
                "low": 0.1213011241,
                "close": 0.1419745231,
                "volume": 162.69,
                "marketCap": 3013126.16,
                "timestamp": "2021-11-11T23:59:59.999Z"
            }
        },
        {
            "timeOpen": "2021-11-12T00:00:00.000Z",
            "timeClose": "2021-11-12T23:59:59.999Z",
            "timeHigh": "2021-11-12T02:16:02.000Z",
            "timeLow": "2021-11-12T16:47:02.000Z",
            "quote": {
                "open": 0.1422404126,
                "high": 0.1433591808,
                "low": 0.1125127132,
                "close": 0.1159743634,
                "volume": 0.0,
                "marketCap": 2461348.51,
                "timestamp": "2021-11-12T23:59:59.999Z"
            }
        },
        {
            "timeOpen": "2021-11-13T00:00:00.000Z",
            "timeClose": "2021-11-13T23:59:59.999Z",
            "timeHigh": "2021-11-13T16:03:02.000Z",
            "timeLow": "2021-11-13T10:03:02.000Z",
            "quote": {
                "open": 0.115801475,
                "high": 0.1171727931,
                "low": 0.1142632396,
                "close": 0.1163825715,
                "volume": 0.0,
                "marketCap": 2470033.17,
                "timestamp": "2021-11-13T23:59:59.999Z"
            }
        },
        {
            "timeOpen": "2021-11-14T00:00:00.000Z",
            "timeClose": "2021-11-14T23:59:59.999Z",
            "timeHigh": "2021-11-14T23:58:03.000Z",
            "timeLow": "2021-11-14T16:55:03.000Z",
            "quote": {
                "open": 0.1163674999,
                "high": 0.1182188008,
                "low": 0.1148842939,
                "close": 0.1181626828,
                "volume": 0.0,
                "marketCap": 2507837.4,
                "timestamp": "2021-11-14T23:59:59.999Z"
            }
        },
        {
            "timeOpen": "2021-11-15T00:00:00.000Z",
            "timeClose": "2021-11-15T23:59:59.999Z",
            "timeHigh": "2021-11-15T09:16:03.000Z",
            "timeLow": "2021-11-15T22:22:03.000Z",
            "quote": {
                "open": 0.118167648,
                "high": 0.1196382333,
                "low": 0.1147043989,
                "close": 0.1149115242,
                "volume": 0.0,
                "marketCap": 2438867.49,
                "timestamp": "2021-11-15T23:59:59.999Z"
            }
        },
        {
            "timeOpen": "2021-11-16T00:00:00.000Z",
            "timeClose": "2021-11-16T23:59:59.999Z",
            "timeHigh": "2021-11-16T00:01:02.000Z",
            "timeLow": "2021-11-16T10:16:03.000Z",
            "quote": {
                "open": 0.1147219581,
                "high": 0.1150167573,
                "low": 0.1065244886,
                "close": 0.1087000001,
                "volume": 0.0,
                "marketCap": 2307052.83,
                "timestamp": "2021-11-16T23:59:59.999Z"
            }
        },
        {
            "timeOpen": "2021-11-17T00:00:00.000Z",
            "timeClose": "2021-11-17T23:59:59.999Z",
            "timeHigh": "2021-11-17T12:01:03.000Z",
            "timeLow": "2021-11-17T10:38:03.000Z",
            "quote": {
                "open": 0.1085910509,
                "high": 0.109786617,
                "low": 0.1056203149,
                "close": 0.108910899,
                "volume": 0.0,
                "marketCap": 2311544.75,
                "timestamp": "2021-11-17T23:59:59.999Z"
            }
        },
        {
            "timeOpen": "2021-11-18T00:00:00.000Z",
            "timeClose": "2021-11-18T23:59:59.999Z",
            "timeHigh": "2021-11-18T01:36:03.000Z",
            "timeLow": "2021-11-18T23:19:03.000Z",
            "quote": {
                "open": 0.1089642613,
                "high": 0.1100120397,
                "low": 0.1020741789,
                "close": 0.1027571406,
                "volume": 0.0,
                "marketCap": 2181121.84,
                "timestamp": "2021-11-18T23:59:59.999Z"
            }
        },
        {
            "timeOpen": "2021-11-19T00:00:00.000Z",
            "timeClose": "2021-11-19T23:59:59.999Z",
            "timeHigh": "2021-11-19T17:30:02.000Z",
            "timeLow": "2021-11-19T03:47:03.000Z",
            "quote": {
                "open": 0.1027805559,
                "high": 0.1053237594,
                "low": 0.1005478511,
                "close": 0.1049531496,
                "volume": 0.0,
                "marketCap": 2227868.64,
                "timestamp": "2021-11-19T23:59:59.999Z"
            }
        },
        {
            "timeOpen": "2021-11-20T00:00:00.000Z",
            "timeClose": "2021-11-20T23:59:59.999Z",
            "timeHigh": "2021-11-20T23:56:02.000Z",
            "timeLow": "2021-11-20T16:21:02.000Z",
            "quote": {
                "open": 0.104905835,
                "high": 0.1080470842,
                "low": 0.1037328548,
                "close": 0.1077873275,
                "volume": 0.0,
                "marketCap": 2288132.35,
                "timestamp": "2021-11-20T23:59:59.999Z"
            }
        },
        {
            "timeOpen": "2021-11-21T00:00:00.000Z",
            "timeClose": "2021-11-21T23:59:59.999Z",
            "timeHigh": "2021-11-21T17:03:02.000Z",
            "timeLow": "2021-11-21T10:44:02.000Z",
            "quote": {
                "open": 0.1077534408,
                "high": 0.1083079896,
                "low": 0.1058071712,
                "close": 0.1058740367,
                "volume": 0.0,
                "marketCap": 2247582.78,
                "timestamp": "2021-11-21T23:59:59.999Z"
            }
        },
        {
            "timeOpen": "2021-11-22T00:00:00.000Z",
            "timeClose": "2021-11-22T23:59:59.999Z",
            "timeHigh": "2021-11-22T14:03:03.000Z",
            "timeLow": "2021-11-22T13:21:02.000Z",
            "quote": {
                "open": 0.1060085103,
                "high": 0.12571341,
                "low": 0.1024076117,
                "close": 0.1200157475,
                "volume": 124.39,
                "marketCap": 2547859.91,
                "timestamp": "2021-11-22T23:59:59.999Z"
            }
        },
        {
            "timeOpen": "2021-11-23T00:00:00.000Z",
            "timeClose": "2021-11-23T23:59:59.999Z",
            "timeHigh": "2021-11-23T10:27:03.000Z",
            "timeLow": "2021-11-23T14:44:03.000Z",
            "quote": {
                "open": 0.119896182,
                "high": 0.1227616009,
                "low": 0.1007046621,
                "close": 0.1022391768,
                "volume": 0.0,
                "marketCap": 2170487.84,
                "timestamp": "2021-11-23T23:59:59.999Z"
            }
        },
        {
            "timeOpen": "2021-11-24T00:00:00.000Z",
            "timeClose": "2021-11-24T23:59:59.999Z",
            "timeHigh": "2021-11-24T00:40:02.000Z",
            "timeLow": "2021-11-24T14:48:02.000Z",
            "quote": {
                "open": 0.1021851079,
                "high": 0.1026004431,
                "low": 0.0993364924,
                "close": 0.0999115107,
                "volume": 1.0,
                "marketCap": 2121073.42,
                "timestamp": "2021-11-24T23:59:59.999Z"
            }
        },
        {
            "timeOpen": "2021-11-25T00:00:00.000Z",
            "timeClose": "2021-11-25T23:59:59.999Z",
            "timeHigh": "2021-11-25T16:07:02.000Z",
            "timeLow": "2021-11-25T00:12:02.000Z",
            "quote": {
                "open": 0.1015413016,
                "high": 0.1053781432,
                "low": 0.1014353662,
                "close": 0.1018327766,
                "volume": 1.0,
                "marketCap": 2161867.9,
                "timestamp": "2021-11-25T23:59:59.999Z"
            }
        },
        {
            "timeOpen": "2021-11-26T00:00:00.000Z",
            "timeClose": "2021-11-26T23:59:59.999Z",
            "timeHigh": "2021-11-26T00:18:02.000Z",
            "timeLow": "2021-11-26T23:59:02.000Z",
            "quote": {
                "open": 0.1045769821,
                "high": 0.1050506796,
                "low": 0.0951373724,
                "close": 0.0951373724,
                "volume": 0.0,
                "marketCap": 2019738.16,
                "timestamp": "2021-11-26T23:59:59.999Z"
            }
        },
        {
            "timeOpen": "2021-11-27T00:00:00.000Z",
            "timeClose": "2021-11-27T23:59:59.999Z",
            "timeHigh": "2021-11-27T08:38:02.000Z",
            "timeLow": "2021-11-27T00:00:02.000Z",
            "quote": {
                "open": 0.095086331,
                "high": 0.0982094359,
                "low": 0.095086331,
                "close": 0.0970239778,
                "volume": 0.0,
                "marketCap": 2059796.74,
                "timestamp": "2021-11-27T23:59:59.999Z"
            }
        },
        {
            "timeOpen": "2021-11-28T00:00:00.000Z",
            "timeClose": "2021-11-28T23:59:59.999Z",
            "timeHigh": "2021-11-28T23:34:07.000Z",
            "timeLow": "2021-11-28T18:44:02.000Z",
            "quote": {
                "open": 0.0972967658,
                "high": 0.1018740727,
                "low": 0.0950987061,
                "close": 0.1015518636,
                "volume": 0.0,
                "marketCap": 2155931.85,
                "timestamp": "2021-11-28T23:59:59.999Z"
            }
        },
        {
            "timeOpen": "2021-11-29T00:00:00.000Z",
            "timeClose": "2021-11-29T23:59:59.999Z",
            "timeHigh": "2021-11-29T18:29:03.000Z",
            "timeLow": "2021-11-29T09:57:03.000Z",
            "quote": {
                "open": 0.1016160136,
                "high": 0.104499363,
                "low": 0.1008067326,
                "close": 0.1026143312,
                "volume": 0.0,
                "marketCap": 2178494.87,
                "timestamp": "2021-11-29T23:59:59.999Z"
            }
        },
        {
            "timeOpen": "2021-11-30T00:00:00.000Z",
            "timeClose": "2021-11-30T23:59:59.999Z",
            "timeHigh": "2021-11-30T15:33:07.000Z",
            "timeLow": "2021-11-30T06:19:39.000Z",
            "quote": {
                "open": 0.102606655,
                "high": 0.1048689794,
                "low": 0.099501676,
                "close": 0.1012297277,
                "volume": 0.0,
                "marketCap": 2149106.52,
                "timestamp": "2021-11-30T23:59:59.999Z"
            }
        }
    ]
}