{
    "id": 16,
    "name": "WorldCoin",
    "symbol": "WDC",
    "quotes": [
        {
            "timeOpen": "2021-12-01T00:00:00.000Z",
            "timeClose": "2021-12-01T23:59:59.999Z",
            "timeHigh": "2021-12-01T02:54:32.000Z",
            "timeLow": "2021-12-01T07:58:33.000Z",
            "quote": {
                "open": 0.0464132579,
                "high": 0.0471521233,
                "low": 0.0413941216,
                "close": 0.0466138566,
                "volume": 124.44,
                "marketCap": 0.0,
                "timestamp": "2021-12-01T23:59:59.999Z"
            }
        },
        {
            "timeOpen": "2021-12-02T00:00:00.000Z",
            "timeClose": "2021-12-02T23:59:59.999Z",
            "timeHigh": "2021-12-02T01:06:14.000Z",
            "timeLow": "2021-12-02T20:50:03.000Z",
            "quote": {
                "open": 0.0466125052,
                "high": 0.0466931312,
                "low": 0.0399268997,
                "close": 0.0409700479,
                "volume": 2387.04,
                "marketCap": 0.0,
                "timestamp": "2021-12-02T23:59:59.999Z"
            }
        },
        {
            "timeOpen": "2021-12-03T00:00:00.000Z",
            "timeClose": "2021-12-03T23:59:59.999Z",
            "timeHigh": "2021-12-03T11:36:03.000Z",
            "timeLow": "2021-12-03T20:41:03.000Z",
            "quote": {
                "open": 0.0410071467,
                "high": 0.0445674443,
                "low": 0.0379407402,
                "close": 0.0380254746,
                "volume": 2183.47,
                "marketCap": 0.0,
                "timestamp": "2021-12-03T23:59:59.999Z"
            }
        },
        {
            "timeOpen": "2021-12-04T00:00:00.000Z",
            "timeClose": "2021-12-04T23:59:59.999Z",
            "timeHigh": "2021-12-04T05:10:02.000Z",
            "timeLow": "2021-12-04T23:58:03.000Z",
            "quote": {
                "open": 0.0380234606,
                "high": 0.0381751968,
                "low": 0.0299971439,
                "close": 0.0300025439,
                "volume": 4244.23,
                "marketCap": 0.0,
                "timestamp": "2021-12-04T23:59:59.999Z"
            }
        },
        {
            "timeOpen": "2021-12-05T00:00:00.000Z",
            "timeClose": "2021-12-05T23:59:59.999Z",
            "timeHigh": "2021-12-05T16:49:03.000Z",
            "timeLow": "2021-12-05T00:01:03.000Z",
            "quote": {
                "open": 0.0300002039,
                "high": 0.0368453078,
                "low": 0.0299958239,
                "close": 0.0303150595,
                "volume": 123.38,
                "marketCap": 0.0,
                "timestamp": "2021-12-05T23:59:59.999Z"
            }
        },
        {
            "timeOpen": "2021-12-06T00:00:00.000Z",
            "timeClose": "2021-12-06T23:59:59.999Z",
            "timeHigh": "2021-12-06T17:10:03.000Z",
            "timeLow": "2021-12-06T00:02:03.000Z",
            "quote": {
                "open": 0.030319096,
                "high": 0.0329027099,
                "low": 0.0303179675,
                "close": 0.0305286247,
                "volume": 955.34,
                "marketCap": 0.0,
                "timestamp": "2021-12-06T23:59:59.999Z"
            }
        },
        {
            "timeOpen": "2021-12-07T00:00:00.000Z",
            "timeClose": "2021-12-07T23:59:59.999Z",
            "timeHigh": "2021-12-07T05:27:03.000Z",
            "timeLow": "2021-12-07T09:59:03.000Z",
            "quote": {
                "open": 0.0305415322,
                "high": 0.036351361,
                "low": 0.0300779548,
                "close": 0.0306308919,
                "volume": 1119.93,
                "marketCap": 0.0,
                "timestamp": "2021-12-07T23:59:59.999Z"
            }
        },
        {
            "timeOpen": "2021-12-08T00:00:00.000Z",
            "timeClose": "2021-12-08T23:59:59.999Z",
            "timeHigh": "2021-12-08T09:22:03.000Z",
            "timeLow": "2021-12-08T01:44:03.000Z",
            "quote": {
                "open": 0.0306297426,
                "high": 0.043543244,
                "low": 0.0305765309,
                "close": 0.0331155859,
                "volume": 4527.1,
                "marketCap": 0.0,
                "timestamp": "2021-12-08T23:59:59.999Z"
            }
        },
        {
            "timeOpen": "2021-12-09T00:00:00.000Z",
            "timeClose": "2021-12-09T23:59:59.999Z",
            "timeHigh": "2021-12-09T23:29:02.000Z",
            "timeLow": "2021-12-09T08:28:03.000Z",
            "quote": {
                "open": 0.0330790162,
                "high": 0.0391772695,
                "low": 0.0317519926,
                "close": 0.0391194908,
                "volume": 817.21,
                "marketCap": 0.0,
                "timestamp": "2021-12-09T23:59:59.999Z"
            }
        },
        {
            "timeOpen": "2021-12-10T00:00:00.000Z",
            "timeClose": "2021-12-10T23:59:59.999Z",
            "timeHigh": "2021-12-10T00:37:02.000Z",
            "timeLow": "2021-12-10T20:35:03.000Z",
            "quote": {
                "open": 0.0391344728,
                "high": 0.0391758654,
                "low": 0.0306789567,
                "close": 0.0352647346,
                "volume": 1830.71,
                "marketCap": 0.0,
                "timestamp": "2021-12-10T23:59:59.999Z"
            }
        },
        {
            "timeOpen": "2021-12-11T00:00:00.000Z",
            "timeClose": "2021-12-11T23:59:59.999Z",
            "timeHigh": "2021-12-11T02:40:03.000Z",
            "timeLow": "2021-12-11T20:51:03.000Z",
            "quote": {
                "open": 0.0352612498,
                "high": 0.0352702634,
                "low": 0.0298661092,
                "close": 0.0299201016,
                "volume": 2529.58,
                "marketCap": 0.0,
                "timestamp": "2021-12-11T23:59:59.999Z"
            }
        },
        {
            "timeOpen": "2021-12-12T00:00:00.000Z",
            "timeClose": "2021-12-12T23:59:59.999Z",
            "timeHigh": "2021-12-12T11:38:03.000Z",
            "timeLow": "2021-12-12T00:30:03.000Z",
            "quote": {
                "open": 0.0299166228,
                "high": 0.0349233229,
                "low": 0.0298566137,
                "close": 0.0300169945,
                "volume": 3261.6,
                "marketCap": 0.0,
                "timestamp": "2021-12-12T23:59:59.999Z"
            }
        },
        {
            "timeOpen": "2021-12-13T00:00:00.000Z",
            "timeClose": "2021-12-13T23:59:59.999Z",
            "timeHigh": "2021-12-13T05:13:02.000Z",
            "timeLow": "2021-12-13T22:59:03.000Z",
            "quote": {
                "open": 0.0300315153,
                "high": 0.0338671123,
                "low": 0.0279950271,
                "close": 0.0280037818,
                "volume": 5624.22,
                "marketCap": 0.0,
                "timestamp": "2021-12-13T23:59:59.999Z"
            }
        },
        {
            "timeOpen": "2021-12-14T00:00:00.000Z",
            "timeClose": "2021-12-14T23:59:59.999Z",
            "timeHigh": "2021-12-14T16:11:03.000Z",
            "timeLow": "2021-12-14T12:58:03.000Z",
            "quote": {
                "open": 0.0280036548,
                "high": 0.0284567083,
                "low": 0.0279490623,
                "close": 0.0280167294,
                "volume": 5934.67,
                "marketCap": 0.0,
                "timestamp": "2021-12-14T23:59:59.999Z"
            }
        },
        {
            "timeOpen": "2021-12-15T00:00:00.000Z",
            "timeClose": "2021-12-15T23:59:59.999Z",
            "timeHigh": "2021-12-15T13:36:03.000Z",
            "timeLow": "2021-12-15T21:59:03.000Z",
            "quote": {
                "open": 0.0280127454,
                "high": 0.0321313039,
                "low": 0.0279480713,
                "close": 0.0280115498,
                "volume": 1729.33,
                "marketCap": 0.0,
                "timestamp": "2021-12-15T23:59:59.999Z"
            }
        },
        {
            "timeOpen": "2021-12-16T00:00:00.000Z",
            "timeClose": "2021-12-16T23:59:59.999Z",
            "timeHigh": "2021-12-16T21:23:03.000Z",
            "timeLow": "2021-12-16T00:31:03.000Z",
            "quote": {
                "open": 0.028011263,
                "high": 0.0282561349,
                "low": 0.0279924338,
                "close": 0.0282032846,
                "volume": 157.32,
                "marketCap": 0.0,
                "timestamp": "2021-12-16T23:59:59.999Z"
            }
        },
        {
            "timeOpen": "2021-12-17T00:00:00.000Z",
            "timeClose": "2021-12-17T23:59:59.999Z",
            "timeHigh": "2021-12-17T19:05:03.000Z",
            "timeLow": "2021-12-17T16:08:03.000Z",
            "quote": {
                "open": 0.0282073429,
                "high": 0.0332662585,
                "low": 0.0279546213,
                "close": 0.0280073539,
                "volume": 622.32,
                "marketCap": 0.0,
                "timestamp": "2021-12-17T23:59:59.999Z"
            }
        },
        {
            "timeOpen": "2021-12-18T00:00:00.000Z",
            "timeClose": "2021-12-18T23:59:59.999Z",
            "timeHigh": "2021-12-18T15:14:03.000Z",
            "timeLow": "2021-12-18T14:01:04.000Z",
            "quote": {
                "open": 0.028023475,
                "high": 0.0280551263,
                "low": 0.0279532241,
                "close": 0.0280086799,
                "volume": 841.35,
                "marketCap": 0.0,
                "timestamp": "2021-12-18T23:59:59.999Z"
            }
        },
        {
            "timeOpen": "2021-12-19T00:00:00.000Z",
            "timeClose": "2021-12-19T23:59:59.999Z",
            "timeHigh": "2021-12-19T05:50:03.000Z",
            "timeLow": "2021-12-19T00:45:03.000Z",
            "quote": {
                "open": 0.0280051239,
                "high": 0.0333035886,
                "low": 0.027965453,
                "close": 0.0319098385,
                "volume": 899.77,
                "marketCap": 0.0,
                "timestamp": "2021-12-19T23:59:59.999Z"
            }
        },
        {
            "timeOpen": "2021-12-20T00:00:00.000Z",
            "timeClose": "2021-12-20T23:59:59.999Z",
            "timeHigh": "2021-12-20T02:47:02.000Z",
            "timeLow": "2021-12-20T22:48:03.000Z",
            "quote": {
                "open": 0.0318996124,
                "high": 0.0319637183,
                "low": 0.0279460428,
                "close": 0.0279692142,
                "volume": 950.91,
                "marketCap": 0.0,
                "timestamp": "2021-12-20T23:59:59.999Z"
            }
        },
        {
            "timeOpen": "2021-12-21T00:00:00.000Z",
            "timeClose": "2021-12-21T23:59:59.999Z",
            "timeHigh": "2021-12-21T23:57:03.000Z",
            "timeLow": "2021-12-21T01:02:02.000Z",
            "quote": {
                "open": 0.0279711947,
                "high": 0.0318119454,
                "low": 0.0279684853,
                "close": 0.031808888,
                "volume": 196.28,
                "marketCap": 0.0,
                "timestamp": "2021-12-21T23:59:59.999Z"
            }
        },
        {
            "timeOpen": "2021-12-22T00:00:00.000Z",
            "timeClose": "2021-12-22T23:59:59.999Z",
            "timeHigh": "2021-12-22T03:23:02.000Z",
            "timeLow": "2021-12-22T19:55:06.000Z",
            "quote": {
                "open": 0.0318126119,
                "high": 0.042008363,
                "low": 0.028743229,
                "close": 0.0288114955,
                "volume": 4471.27,
                "marketCap": 0.0,
                "timestamp": "2021-12-22T23:59:59.999Z"
            }
        },
        {
            "timeOpen": "2021-12-23T00:00:00.000Z",
            "timeClose": "2021-12-23T23:59:59.999Z",
            "timeHigh": "2021-12-23T11:45:03.000Z",
            "timeLow": "2021-12-23T07:10:05.000Z",
            "quote": {
                "open": 0.0288095535,
                "high": 0.028926076,
                "low": 0.0287622471,
                "close": 0.0289076636,
                "volume": 2045.03,
                "marketCap": 0.0,
                "timestamp": "2021-12-23T23:59:59.999Z"
            }
        },
        {
            "timeOpen": "2021-12-24T00:00:00.000Z",
            "timeClose": "2021-12-24T23:59:59.999Z",
            "timeHigh": "2021-12-24T10:12:03.000Z",
            "timeLow": "2021-12-24T00:03:03.000Z",
            "quote": {
                "open": 0.0289112129,
                "high": 0.0305235457,
                "low": 0.0289073411,
                "close": 0.0300356713,
                "volume": 566.16,
                "marketCap": 0.0,
                "timestamp": "2021-12-24T23:59:59.999Z"
            }
        },
        {
            "timeOpen": "2021-12-25T00:00:00.000Z",
            "timeClose": "2021-12-25T23:59:59.999Z",
            "timeHigh": "2021-12-25T01:13:04.000Z",
            "timeLow": "2021-12-25T16:51:03.000Z",
            "quote": {
                "open": 0.0300360587,
                "high": 0.0301451007,
                "low": 0.0299407857,
                "close": 0.0299959997,
                "volume": 545.45,
                "marketCap": 0.0,
                "timestamp": "2021-12-25T23:59:59.999Z"
            }
        },
        {
            "timeOpen": "2021-12-26T00:00:00.000Z",
            "timeClose": "2021-12-26T23:59:59.999Z",
            "timeHigh": "2021-12-26T18:16:04.000Z",
            "timeLow": "2021-12-26T05:12:08.000Z",
            "quote": {
                "open": 0.0299976797,
                "high": 0.0353225158,
                "low": 0.0299440876,
                "close": 0.0300176618,
                "volume": 335.94,
                "marketCap": 0.0,
                "timestamp": "2021-12-26T23:59:59.999Z"
            }
        },
        {
            "timeOpen": "2021-12-27T00:00:00.000Z",
            "timeClose": "2021-12-27T23:59:59.999Z",
            "timeHigh": "2021-12-27T02:48:03.000Z",
            "timeLow": "2021-12-27T20:46:03.000Z",
            "quote": {
                "open": 0.0300134618,
                "high": 0.0300598352,
                "low": 0.029441268,
                "close": 0.0294897132,
                "volume": 203.51,
                "marketCap": 0.0,
                "timestamp": "2021-12-27T23:59:59.999Z"
            }
        },
        {
            "timeOpen": "2021-12-28T00:00:00.000Z",
            "timeClose": "2021-12-28T23:59:59.999Z",
            "timeHigh": "2021-12-28T01:01:03.000Z",
            "timeLow": "2021-12-28T16:31:03.000Z",
            "quote": {
                "open": 0.029498337,
                "high": 0.0295500126,
                "low": 0.0279577912,
                "close": 0.0280368192,
                "volume": 5679.22,
                "marketCap": 0.0,
                "timestamp": "2021-12-28T23:59:59.999Z"
            }
        },
        {
            "timeOpen": "2021-12-29T00:00:00.000Z",
            "timeClose": "2021-12-29T23:59:59.999Z",
            "timeHigh": "2021-12-29T21:31:08.000Z",
            "timeLow": "2021-12-29T03:20:03.000Z",
            "quote": {
                "open": 0.0280326916,
                "high": 0.0358698627,
                "low": 0.0210925384,
                "close": 0.0358082852,
                "volume": 6115.75,
                "marketCap": 0.0,
                "timestamp": "2021-12-29T23:59:59.999Z"
            }
        },
        {
            "timeOpen": "2021-12-30T00:00:00.000Z",
            "timeClose": "2021-12-30T23:59:59.999Z",
            "timeHigh": "2021-12-30T05:02:03.000Z",
            "timeLow": "2021-12-30T09:03:03.000Z",
            "quote": {
                "open": 0.0358105117,
                "high": 0.0358593001,
                "low": 0.0346410252,
                "close": 0.0347337029,
                "volume": 295.35,
                "marketCap": 0.0,
                "timestamp": "2021-12-30T23:59:59.999Z"
            }
        },
        {
            "timeOpen": "2021-12-31T00:00:00.000Z",
            "timeClose": "2021-12-31T23:59:59.999Z",
            "timeHigh": "2021-12-31T00:00:03.000Z",
            "timeLow": "2021-12-31T02:02:02.000Z",
            "quote": {
                "open": 0.0347359443,
                "high": 0.0347359443,
                "low": 0.034008368,
                "close": 0.0347067529,
                "volume": 0.0,
                "marketCap": 0.0,
                "timestamp": "2021-12-31T23:59:59.999Z"
            }
        }
    ]
}